mqclient_redirect/__init__.py
wipac_mqclient-1.0.1.dist-info/LICENSE
wipac_mqclient-1.0.1.dist-info/METADATA
wipac_mqclient-1.0.1.dist-info/WHEEL
wipac_mqclient-1.0.1.dist-info/top_level.txt
wipac_mqclient-1.0.1.dist-info/RECORD
