Metadata-Version: 2.1
Name: wipac-mqclient
Version: 1.0.1
Summary: Serves as a redirect for PyPI to the newer https://github.com/Observation-Management-Service/MQClient
Home-page: https://github.com/WIPACrepo/mqclient-deprecated
Download-URL: https://pypi.org/project/wipac-mqclient/
Author: WIPAC Developers
Author-email: developers@icecube.wisc.edu
License: MIT
Project-URL: Tracker, https://github.com/Observation-Management-Service/MQClient/issues
Project-URL: Source, https://github.com/Observation-Management-Service/MQClient
Classifier: Development Status :: 7 - Inactive
Classifier: License :: OSI Approved :: MIT License
Classifier: Programming Language :: Python :: 3
License-File: LICENSE
Requires-Dist: oms-mqclient
Provides-Extra: all
Requires-Dist: oms-mqclient[pulsar] ; extra == 'all'
Requires-Dist: oms-mqclient[rabbitmq] ; extra == 'all'
Requires-Dist: oms-mqclient[gcp] ; extra == 'all'
Requires-Dist: oms-mqclient[nats] ; extra == 'all'
Provides-Extra: gcp
Requires-Dist: oms-mqclient[gcp] ; extra == 'gcp'
Provides-Extra: nats
Requires-Dist: oms-mqclient[nats] ; extra == 'nats'
Provides-Extra: pulsar
Requires-Dist: oms-mqclient[pulsar] ; extra == 'pulsar'
Provides-Extra: rabbitmq
Requires-Dist: oms-mqclient[rabbitmq] ; extra == 'rabbitmq'
Provides-Extra: telemetry
Requires-Dist: oms-mqclient[telemetry] ; extra == 'telemetry'
